pyhail/__init__.py
pyhail/__version__.py
pyhail/common.py
pyhail/hacc.py
pyhail/hdr.py
pyhail/hsda.py
pyhail/hsda_mf.py
pyhail/mesh_grid.py
pyhail/mesh_ppi.py
pyhail-3.2.2.dist-info/licenses/LICENSE
pyhail-3.2.2.dist-info/METADATA
pyhail-3.2.2.dist-info/WHEEL
pyhail-3.2.2.dist-info/top_level.txt
pyhail-3.2.2.dist-info/RECORD
