Metadata-Version: 2.4
Name: pyhail
Version: 3.2.2
Summary: Python hail retreivals
Home-page: https://github.com/joshuass/pyhail
Author: Joshua Soderholm
Author-email: Joshua Soderholm <joshua.soderholm@bom.gov.au>
Project-URL: Homepage, https://github.com/joshua-wx/pyhail
Project-URL: Bug Tracker, https://github.com/joshua-wx/pyhail/issues
Keywords: radar,weather,meteorology,calibration
Classifier: Programming Language :: Python :: 3
Classifier: License :: OSI Approved :: MIT License
Classifier: Operating System :: OS Independent
Requires-Python: >=3.9
License-File: LICENSE
Requires-Dist: numpy
Requires-Dist: scipy
Requires-Dist: numba>=0.59.1
Dynamic: author
Dynamic: home-page
Dynamic: license-file
Dynamic: requires-python
